dash_auth0/__init__.py
dash_auth0/auth.py
dash_auth0/auth0_auth.py
dash_auth0-0.1.6.dist-info/LICENSE
dash_auth0-0.1.6.dist-info/METADATA
dash_auth0-0.1.6.dist-info/WHEEL
dash_auth0-0.1.6.dist-info/RECORD
