Metadata-Version: 2.1
Name: dash-auth0
Version: 0.1.6
Summary: Authenticate your Dash app with Auth0
License: MIT
Author: Daniele Brambilla
Author-email: daniele.bram@gmail.com
Requires-Python: >=3.10,<4.0
Classifier: License :: OSI Approved :: MIT License
Classifier: Programming Language :: Python :: 3
Classifier: Programming Language :: Python :: 3.10
Classifier: Programming Language :: Python :: 3.11
Requires-Dist: authlib (>=1.2.1,<2.0.0)
Requires-Dist: dash (>=2.13.0,<3.0.0)
